{"chunk_definitions":[{"row":21,"row_count":1,"visible":true,"expansion_state":0,"options":{"engine":"r","label":"setup","include":false,"eval":true},"document_id":"48941565","chunk_id":"csetup_chunk","chunk_label":"setup"},{"row":68,"row_count":1,"visible":true,"expansion_state":0,"options":{"engine":"r","label":"libraries","include":false,"eval":true},"document_id":"48941565","chunk_id":"cmsknw56x13j7","chunk_label":"libraries"},{"row":112,"row_count":1,"visible":true,"expansion_state":0,"options":{"engine":"r","label":"dataprocess","eval":true,"include":false},"document_id":"48941565","chunk_id":"crg0e4g97msn4","chunk_label":"dataprocess"},{"row":462,"row_count":1,"visible":true,"expansion_state":0,"options":{"engine":"r","label":"tokenization, eda1","eval":true,"fig.show":true,"fig.cap":"Figure 2: Bar plots showing the 20 most frequently used (a) words and (b) bigrams used by all presidents"},"document_id":"48941565","chunk_id":"cy8mnpugqkd2i","chunk_label":"tokenization"},{"row":527,"row_count":1,"visible":true,"expansion_state":0,"options":{"engine":"r","label":"eda1","eval":true,"fig.show":true,"fig.cap":"Figure 3: Bar plots showing the 20 most frequently used words by each president. "},"document_id":"48941565","chunk_id":"ciaikkn1h62ig","chunk_label":"eda1"},{"row":595,"row_count":1,"visible":true,"expansion_state":0,"options":{"engine":"r","label":"eda2","eval":true,"fig.show":true,"fig.cap":"Figure 4: Bar plots showing the 20 most frequently used bigrams by each president. "},"document_id":"48941565","chunk_id":"cj5plxoojjw9o","chunk_label":"eda2"},{"row":637,"row_count":1,"visible":true,"expansion_state":0,"options":{"engine":"r","label":"eda3","eval":true,"include":false},"document_id":"48941565","chunk_id":"cia6cd0j0t882","chunk_label":"eda3"},{"row":660,"row_count":1,"visible":true,"expansion_state":0,"options":{"engine":"r","label":"eda4","eval":true,"fig.show":true,"fig.cap":"Figure 5: Bar plots showing (a) the average number of sentences per speech and (b) the average number of words per sentence for each president."},"document_id":"48941565","chunk_id":"c3upwxcegsodm","chunk_label":"eda4"},{"row":698,"row_count":1,"visible":true,"expansion_state":0,"options":{"engine":"r","label":"bow","eval":true,"include":false},"document_id":"48941565","chunk_id":"cbwu6h1mugsdw","chunk_label":"bow"},{"row":750,"row_count":1,"visible":true,"expansion_state":0,"options":{"engine":"r","label":"bowSplits","eval":true,"include":false},"document_id":"48941565","chunk_id":"c2qn76loghcpe","chunk_label":"bowSplits"},{"row":987,"row_count":1,"visible":true,"expansion_state":0,"options":{"engine":"r","label":"bowClassTree","eval":true,"include":false},"document_id":"48941565","chunk_id":"cbpqcgrao844j","chunk_label":"bowClassTree"},{"row":1215,"row_count":1,"visible":true,"expansion_state":0,"options":{"engine":"r","label":"bowRF","eval":true,"include":false},"document_id":"F3ABFF1E","chunk_id":"cwlchzohwaqku","chunk_label":"bowRF"},{"row":1552,"row_count":1,"visible":true,"expansion_state":0,"options":{"engine":"r","label":"bowXGB","eval":true,"include":false},"document_id":"F3ABFF1E","chunk_id":"c06ivokl8vzpx","chunk_label":"bowXGB"},{"row":2212,"row_count":1,"visible":true,"expansion_state":0,"options":{},"document_id":"F3ABFF1E","chunk_id":"cnf523msvf3cf","chunk_label":"addendum1"},{"row":1750,"row_count":1,"visible":true,"expansion_state":0,"options":{"engine":"r","label":"bowNB","eval":true,"include":false},"document_id":"F3ABFF1E","chunk_id":"co7zp08wu7ald","chunk_label":"bowNB"},{"row":2170,"row_count":1,"visible":true,"expansion_state":0,"options":{},"document_id":"F3ABFF1E","chunk_id":"cbzblh23ur3fj","chunk_label":"tblNN"},{"row":221,"row_count":1,"visible":true,"expansion_state":0,"options":{"engine":"mermaid","label":"unnamed-chunk-1"},"document_id":"F3ABFF1E","chunk_id":"ce9enlijpg7yz","chunk_label":"unnamed-chunk-1"},{"row":2195,"row_count":1,"visible":true,"expansion_state":0,"options":{},"document_id":"F3ABFF1E","chunk_id":"cpvciribhk49t","chunk_label":"bowNN2"}],"doc_write_time":1698084575,"chunk_rendered_width":636,"working_dir":null,"default_chunk_options":{"echo":false,"warnings":false,"message":false}}